<?xml version="1.0" encoding="utf-8" ?>
<filelist>
  <file name="OnSIS Dev"
        location="serverTemplates\\Windows\\OnSISDev.config">
  </file>
  <file name="OnSIS QA"
      location="serverTemplates\\Windows\\OnSISQA.config">
  </file>
  <file name="OnSIS UAT"
      location="serverTemplates\\Windows\\OnSISUAT.config">
  </file>
  <file name="Large Ubuntu 14"
      location="serverTemplates\\Linux\\largeUbun.config">
  </file>
  <file name="Medium Ubuntu 14"
      location="serverTemplates\\Linux\\mediumUbun.config">
  </file>
  <file name="Small Ubuntu 14"
      location="serverTemplates\\Linux\\smallUbun.config">
  </file> 
</filelist>
